{"ShopElements":[{"ProductKind":"FirstAidKit","ProductBody":"Used to heal your starship","ProductAmount":"2.00","PriceKind":"AlianceCredits","PriceAmount":"4.00"},{"ProductKind":"EasyTrigger","ProductBody":"Used to damage the enemy starship","ProductAmount":"3.00","PriceKind":"AlianceCredits","PriceAmount":"8.00"},{"ProductKind":"DeAthomizer","ProductBody":"Allows the player to destroy a single block","ProductAmount":"1.00","PriceKind":"AlianceCredits","PriceAmount":"5.00"},{"ProductKind":"Dilithium","ProductBody":"Grants access to missions","ProductAmount":"5.00","PriceKind":"AlianceCredits","PriceAmount":"1.00"},{"ProductKind":"AlianceCredits","ProductBody":"Used to buy things at the shop","ProductAmount":"100.00","PriceKind":"_","PriceAmount":"0.00"}],"LevelsModel":[]}