{"StarshipColors":[{"SkinName":"RangerBlue","SkinDescription":"Standard Color for your starship (Blue)","ColorCode":"0,2156863-0,2156863-0,2156863_0,745283-0,745283-0,745283_0-0,5-1","Price":"0.00"},{"SkinName":"RangerRed","SkinDescription":"Standard Color for your starship (Red)","ColorCode":"0,2156863-0,2156863-0,2156863_0,745283-0,745283-0,745284_1-0-0","Price":"0.00"},{"SkinName":"RangerGreen","SkinDescription":"Standard Color for your starship (Green)","ColorCode":"0,2156863-0,2156863-0,2156863_0,745283-0,745283-0,745285_0-1-0","Price":"0.00"},{"SkinName":"Elit","SkinDescription":"Used by those who can pay it","ColorCode":"0,05660379-0,05660379-0,05660379_0,2156863-0,2156863-0,2156863_0,9921569-0,7215686-0","Price":"100.00"},{"SkinName":"Void","SkinDescription":"Colors from the abyss","ColorCode":"0,1254902-0,03921569-0,2745098_0,1490196-0,1490196-0,1490196_0,7019608-0-1","Price":"250.00"},{"SkinName":"RedForce","SkinDescription":"You can see the evil in their eyes","ColorCode":"0,1415094-0,1415094-0,1415094_0-0-0_1-0-0","Price":"250.00"}]}